obsidian_callouts/__init__.py
obsidian_callouts/extension.py
obsidian_callouts-1.0.0.dist-info/METADATA
obsidian_callouts-1.0.0.dist-info/WHEEL
obsidian_callouts-1.0.0.dist-info/entry_points.txt
obsidian_callouts-1.0.0.dist-info/licenses/LICENSE
obsidian_callouts-1.0.0.dist-info/RECORD
