Metadata-Version: 2.4
Name: obsidian-callouts
Version: 1.0.0
Summary: A Python-Markdown plugin for Obsidian-style callouts.
Project-URL: Homepage, https://github.com/GooRoo/obsidian-callouts
Project-URL: Issues, https://github.com/GooRoo/obsidian-callouts/issues
Project-URL: Repository, https://github.com/GooRoo/obsidian-callouts.git
Author-email: GooRoo <sergey.olendarenko@gmail.com>
License-Expression: BSD-3-Clause
License-File: LICENSE
Classifier: Development Status :: 5 - Production/Stable
Classifier: Environment :: Plugins
Classifier: License :: OSI Approved :: BSD License
Classifier: Programming Language :: Python :: 3
Classifier: Programming Language :: Python :: 3.10
Classifier: Topic :: Documentation
Classifier: Topic :: Software Development :: Documentation
Classifier: Topic :: Text Processing :: Markup :: HTML
Classifier: Topic :: Text Processing :: Markup :: Markdown
Requires-Python: >=3.10
Requires-Dist: markdown>=3.7
